sessionstash/__init__.py
sessionstash/core.py
sessionstash/main.py
sessionstash-0.1.1.dist-info/LICENSE
sessionstash-0.1.1.dist-info/METADATA
sessionstash-0.1.1.dist-info/WHEEL
sessionstash-0.1.1.dist-info/entry_points.txt
sessionstash-0.1.1.dist-info/top_level.txt
sessionstash-0.1.1.dist-info/RECORD
