Metadata-Version: 2.1
Name: sessionstash
Version: 0.1.1
Summary: Save & restore Python interpreter sessions — an R-style snapshotter powered by dill.
Author-email: Jiwoong Kim <jiwoongbio@gmail.com>
License: MIT
Project-URL: Homepage, https://github.com/jiwoongbio/sessionstash
Project-URL: Issues, https://github.com/jiwoongbio/sessionstash/issues
Requires-Python: >=3.9
License-File: LICENSE
Requires-Dist: dill>=0.3.8
Provides-Extra: dev
Requires-Dist: pytest; extra == "dev"
Requires-Dist: ruff; extra == "dev"
